[
    {
        "img" : "cavalo.png",
        "nome" : "xadrez",
        "funcao" : "voce pode jogar xadrez com um amigo ou entao contra um computador",
        "tecnologias" : "javascript",
        "data" : "05/2025"

    },
    {
        "img" : "aguarde.png",
        "nome" : "Em construção",
        "funcao" : "Em construção",
        "tecnologias" : "javascript",
        "data" : "x/2025"

    },
    {
        "img" : "aguarde.png",
        "nome" : "Em construção",
        "funcao" : "Em construção",
        "tecnologias" : "javascript",
        "data" : "x/2025"

    }
]
